{
  "formatVersion": 1,
  "database": {
    "version": 2,
    "identityHash": "03e15548008ccd2a56b14d0f4e9d93c3",
    "entities": [
      {
        "tableName": "DebitsAndCreditsTable",
        "createSql": "CREATE TABLE IF NOT EXISTS `${TABLE_NAME}` (`transId` INTEGER PRIMARY KEY AUTOINCREMENT NOT NULL, `fkUserId` INTEGER NOT NULL, `Date` INTEGER NOT NULL, `fkPaymentTypeId` INTEGER NOT NULL, `Debit` INTEGER, `Credit` INTEGER, `Balance` INTEGER NOT NULL, `Comments` TEXT NOT NULL)",
        "fields": [
          {
            "fieldPath": "transId",
            "columnName": "transId",
            "affinity": "INTEGER",
            "notNull": true
          },
          {
            "fieldPath": "fkUserId",
            "columnName": "fkUserId",
            "affinity": "INTEGER",
            "notNull": true
          },
          {
            "fieldPath": "Date",
            "columnName": "Date",
            "affinity": "INTEGER",
            "notNull": true
          },
          {
            "fieldPath": "fkPaymentTypeId",
            "columnName": "fkPaymentTypeId",
            "affinity": "INTEGER",
            "notNull": true
          },
          {
            "fieldPath": "Debit",
            "columnName": "Debit",
            "affinity": "INTEGER",
            "notNull": false
          },
          {
            "fieldPath": "Credit",
            "columnName": "Credit",
            "affinity": "INTEGER",
            "notNull": false
          },
          {
            "fieldPath": "Balance",
            "columnName": "Balance",
            "affinity": "INTEGER",
            "notNull": true
          },
          {
            "fieldPath": "Comments",
            "columnName": "Comments",
            "affinity": "TEXT",
            "notNull": true
          }
        ],
        "primaryKey": {
          "columnNames": [
            "transId"
          ],
          "autoGenerate": true
        },
        "indices": [
          {
            "name": "index_DebitsAndCreditsTable_fkUserId_fkPaymentTypeId",
            "unique": true,
            "columnNames": [
              "fkUserId",
              "fkPaymentTypeId"
            ],
            "orders": [],
            "createSql": "CREATE UNIQUE INDEX IF NOT EXISTS `index_DebitsAndCreditsTable_fkUserId_fkPaymentTypeId` ON `${TABLE_NAME}` (`fkUserId`, `fkPaymentTypeId`)"
          },
          {
            "name": "index_DebitsAndCreditsTable_fkUserId",
            "unique": false,
            "columnNames": [
              "fkUserId"
            ],
            "orders": [],
            "createSql": "CREATE INDEX IF NOT EXISTS `index_DebitsAndCreditsTable_fkUserId` ON `${TABLE_NAME}` (`fkUserId`)"
          },
          {
            "name": "index_DebitsAndCreditsTable_fkPaymentTypeId",
            "unique": false,
            "columnNames": [
              "fkPaymentTypeId"
            ],
            "orders": [],
            "createSql": "CREATE INDEX IF NOT EXISTS `index_DebitsAndCreditsTable_fkPaymentTypeId` ON `${TABLE_NAME}` (`fkPaymentTypeId`)"
          }
        ],
        "foreignKeys": []
      },
      {
        "tableName": "UsersTable",
        "createSql": "CREATE TABLE IF NOT EXISTS `${TABLE_NAME}` (`pkUserId` INTEGER PRIMARY KEY AUTOINCREMENT NOT NULL, `UserName` TEXT NOT NULL, FOREIGN KEY(`pkUserId`) REFERENCES `DebitsAndCreditsTable`(`fkUserId`) ON UPDATE NO ACTION ON DELETE CASCADE )",
        "fields": [
          {
            "fieldPath": "pkUserId",
            "columnName": "pkUserId",
            "affinity": "INTEGER",
            "notNull": true
          },
          {
            "fieldPath": "userName",
            "columnName": "UserName",
            "affinity": "TEXT",
            "notNull": true
          }
        ],
        "primaryKey": {
          "columnNames": [
            "pkUserId"
          ],
          "autoGenerate": true
        },
        "indices": [],
        "foreignKeys": [
          {
            "table": "DebitsAndCreditsTable",
            "onDelete": "CASCADE",
            "onUpdate": "NO ACTION",
            "columns": [
              "pkUserId"
            ],
            "referencedColumns": [
              "fkUserId"
            ]
          }
        ]
      }
    ],
    "views": [],
    "setupQueries": [
      "CREATE TABLE IF NOT EXISTS room_master_table (id INTEGER PRIMARY KEY,identity_hash TEXT)",
      "INSERT OR REPLACE INTO room_master_table (id,identity_hash) VALUES(42, '03e15548008ccd2a56b14d0f4e9d93c3')"
    ]
  }
}